wordlift_client/__init__.py
wordlift_client/api_client.py
wordlift_client/api_response.py
wordlift_client/configuration.py
wordlift_client/exceptions.py
wordlift_client/py.typed
wordlift_client/rest.py
wordlift_client/api/__init__.py
wordlift_client/api/account_api.py
wordlift_client/api/account_google_search_console_api.py
wordlift_client/api/account_stats_api.py
wordlift_client/api/accounts_api.py
wordlift_client/api/add_ons_api.py
wordlift_client/api/agent_api.py
wordlift_client/api/ai_visibility_api.py
wordlift_client/api/analyses_api.py
wordlift_client/api/analytics_imports_api.py
wordlift_client/api/analytics_syncs_api.py
wordlift_client/api/audit_api.py
wordlift_client/api/authors_api.py
wordlift_client/api/autocomplete_api.py
wordlift_client/api/botify_crawl_imports_api.py
wordlift_client/api/classifications_api.py
wordlift_client/api/content_evaluations_api.py
wordlift_client/api/content_expansions_api.py
wordlift_client/api/content_generation_completion_api.py
wordlift_client/api/content_generation_fields_api.py
wordlift_client/api/content_generation_models_api.py
wordlift_client/api/content_generation_presets_api.py
wordlift_client/api/content_generation_records_api.py
wordlift_client/api/content_generation_records_export_api.py
wordlift_client/api/content_generation_renders_api.py
wordlift_client/api/content_generation_stats_api.py
wordlift_client/api/content_generation_syncs_api.py
wordlift_client/api/content_generation_word_biases_api.py
wordlift_client/api/content_generations_api.py
wordlift_client/api/custom_domains_api.py
wordlift_client/api/data_uri_api.py
wordlift_client/api/dataset_api.py
wordlift_client/api/default_api.py
wordlift_client/api/embedding_api.py
wordlift_client/api/embeddings_api.py
wordlift_client/api/entities_api.py
wordlift_client/api/entity_gaps_api.py
wordlift_client/api/fact_check_api.py
wordlift_client/api/google_merchants_api.py
wordlift_client/api/google_search_console_api.py
wordlift_client-1.133.0.dist-info/LICENSE
wordlift_client-1.133.0.dist-info/METADATA
wordlift_client-1.133.0.dist-info/WHEEL
wordlift_client-1.133.0.dist-info/top_level.txt
wordlift_client-1.133.0.dist-info/RECORD
