Metadata-Version: 2.1
Name: wordlift-client
Version: 1.133.0
Summary: WordLift API
Home-page: 
Author: WordLift
Author-email: hello@wordlift.io
License: (c) copyright 2022-present WordLift
Keywords: OpenAPI,OpenAPI-Generator,WordLift API
License-File: LICENSE
Requires-Dist: urllib3 <2.1.0,>=1.25.3
Requires-Dist: python-dateutil
Requires-Dist: aiohttp >=3.0.0
Requires-Dist: aiohttp-retry >=2.8.3
Requires-Dist: pydantic >=2
Requires-Dist: typing-extensions >=4.7.1
